{
  "base": "https://qiniucdn.fairyever.com/",
  "prefix": "wdbc-awesome/",
  "library": [
    {
      "id": "kX2H2BZl",
      "size": 256,
      "name": "Folder 1",
      "elements": [
        {
          "id": "U44UF-08V",
          "size": 273475,
          "name": "测试 - 透明图片",
          "url": "1580438783255.png",
          "height": 1200,
          "width": 1200
        },
        {
          "id": "kpDAUGQxT",
          "size": 52206,
          "name": "测试 - 特殊比例 - 高",
          "url": "1580438782951.png",
          "height": 2048,
          "width": 440
        },
        {
          "id": "g_c9CQufj",
          "size": 22931,
          "name": "测试 - 特殊比例 - 宽",
          "url": "1580438782748.png",
          "height": 440,
          "width": 1200
        },
        {
          "id": "tpc-sJ-HF",
          "size": 13585,
          "name": "测试 - 小图",
          "url": "1580438782583.png",
          "height": 440,
          "width": 440
        },
        {
          "id": "wbearvkN9",
          "size": 20063,
          "name": "测试 - 4比3",
          "url": "1580438782168.png",
          "height": 600,
          "width": 800
        }
      ]
    },
    {
      "id": "E7wWyIrJT",
      "size": 224,
      "name": "平面 logo",
      "elements": [
        {
          "id": "9xDa1Bdep",
          "size": 64236,
          "name": "沃德博创 - logo - 文字 - 左右",
          "url": "1580706508138.png",
          "height": 400,
          "width": 1000
        },
        {
          "id": "xsiONxfwx",
          "size": 54956,
          "name": "智慧蛋鸡 - 文字",
          "url": "1580706507935.png",
          "height": 400,
          "width": 1000
        },
        {
          "id": "tiv-sfO_w",
          "size": 38644,
          "name": "智慧蛋鸡 - logo",
          "url": "1580706507700.png",
          "height": 700,
          "width": 700
        },
        {
          "id": "QVcdrNFrk",
          "size": 64800,
          "name": "智慧蛋鸡 - logo - 文字 - 左右",
          "url": "1580706507449.png",
          "height": 400,
          "width": 1000
        },
        {
          "id": "mQO4h-Pmx",
          "size": 104962,
          "name": "智慧蛋鸡 - logo - 文字 - 上下",
          "url": "1580706507013.png",
          "height": 1000,
          "width": 1000
        }
      ]
    }
  ]
}